{
    "audio_ports_port-audios": "-",
    "availability_availability": "Available 2023",
    "bluetooth_bluetooth": "-",
    "bootloader": "U-Boot",
    "brand": "Joy-IT",
    "button_count_numbutton": "1",
    "comment_installation": "For TFTP, rename image to jt-or750i_firmware.bin",
    "comment_recovery": "For TFTP, rename image to jt-or750i_firmware.bin",
    "comments_network_ports_": "2 NICs",
    "cpu": "Qualcomm Atheros QCA9531",
    "cpu_cores_numcores_": "1",
    "cpu_mhz": "550",
    "detachable_antennas_numdetachantenna": "-",
    "device_page_page": "toh:joy-it:jt-or750i",
    "device_type_devicetype": "WiFi Router",
    "ethernet_100m_ports": "4",
    "ethernet_10gbit_ports": "-",
    "ethernet_1gbit_ports": "-",
    "ethernet_2_5gbit_ports": "-",
    "ethernet_5gbit_ports": "-",
    "fccid": "Unknown",
    "firmware_oem_stock_url_url": "http://\u00bf",
    "firmware_openwrt_snapshot_upgrade_url_urls": "https://downloads.openwrt.org/snapshots/targets/ath79/generic/openwrt-ath79-generic-joyit_jt-or750i-squashfs-sysupgrade.bin",
    "firmware_openwrt_upgrade_url_urls": "https://downloads.openwrt.org/releases/22.03.5/targets/ath79/generic/openwrt-22.03.5-ath79-generic-joyit_jt-or750i-squashfs-sysupgrade.bin",
    "flash_mb_mbflashs": "16",
    "forum_search_search-forums": "JT-OR750i",
    "git_search_search-gits": "JT-OR750i",
    "gluon_support_gluonsupport": "Yes",
    "gpios_numgpio": "Unknown",
    "installation_method(s)_method-installations": "U-Boot TFTP recovery, U-Boot web recovery, see git-commit",
    "jtag_yesno": "Unknown",
    "led_count_numled": "1",
    "minipci_ports_port-minipci": "-",
    "model": "JT-OR750i",
    "modem_modem": "-",
    "oem_device_homepage_url_url": "http://\u00bf",
    "openvpn_performance": "Unknown",
    "outdoor_yesno": "No",
    "package_architecture_pkg-arch": "mips_24kc",
    "phone_ports_port-phones": "-",
    "power_supply": "12V, 0.5A",
    "ram_mb_mbram": "128",
    "recovery_method(s)_method-recoverys": "U-Boot TFTP recovery, see git-commit",
    "sata_ports_numsataport": "-",
    "serial": "Yes",
    "serial_connection_parameters_serialparam": "Unknown",
    "serial_connection_voltage_serialvoltage": "Unknown",
    "sfp_plus_ports": "-",
    "sfp_ports": "-",
    "subtarget": "generic",
    "supported_current_rel_releasecurrent": "22.03.5",
    "supported_since_commit_git": "https://git.openwrt.org/?p=openwrt/openwrt.git;a=commit;h=55b4b3655263984b92e4b9fc515a5e6b8003c655",
    "supported_since_rel_releasesince": "21.02.0",
    "switch": "Atheros AR8229 rev. 1",
    "target_target": "ath79",
    "usb_ports": "-",
    "video_ports_port-videos": "-",
    "vlan_yesno": "Yes",
    "where_available": "https://shop.heise.de/router-joy-it-qr750i",
    "wikidevi_url": "Unknown",
    "wireguard_performance": "Unknown",
    "wlan_2_4ghz": "b/g/n",
    "wlan_5_0ghz": "a/n/ac",
    "wlan_driver_wlan-drivers": "ath10k-ct",
    "wlan_hardwares": "Qualcomm Atheros QCA9531, Qualcomm Atheros QCA9887"
}