{
    "audio_ports_port-audios": "-",
    "availability_availability": "Available 2019",
    "bluetooth_bluetooth": "-",
    "bootloader": "RouterBOOT",
    "brand": "MikroTik",
    "button_count_numbutton": "1",
    "comment_installation": "Requires initramfs network boot to install",
    "cpu": "Qualcomm Atheros QCA9533",
    "cpu_cores_numcores_": "1",
    "cpu_mhz": "650",
    "detachable_antennas_numdetachantenna": "-",
    "device_type_devicetype": "Router",
    "ethernet_100m_ports": "5",
    "ethernet_10gbit_ports": "Unknown",
    "ethernet_1gbit_ports": "-",
    "ethernet_2_5gbit_ports": "Unknown",
    "ethernet_5gbit_ports": "Unknown",
    "fccid": "Unknown",
    "firmware_oem_stock_url_url": "http://www.mikrotik.com/download",
    "firmware_openwrt_install_url_urls": "https://downloads.openwrt.org/releases/19.07.10/targets/ar71xx/mikrotik/openwrt-19.07.10-ar71xx-mikrotik-rb-nor-flash-16M-initramfs-kernel.bin",
    "firmware_openwrt_upgrade_url_urls": "https://downloads.openwrt.org/releases/19.07.10/targets/ar71xx/mikrotik/openwrt-19.07.10-ar71xx-mikrotik-rb-nor-flash-16M-squashfs-sysupgrade.bin",
    "flash_mb_mbflashs": "16",
    "forum_search_search-forums": "RB750UPr2 (hEX PoE lite)",
    "git_search_search-gits": "RB750UPr2 (hEX PoE lite)",
    "gluon_support_gluonsupport": "unknown",
    "gpios_numgpio": "Unknown",
    "id": "mikrotik_rb750upr2_hex_poe_lite",
    "installation_method(s)_method-installations": "unknown",
    "jtag_yesno": "Yes",
    "led_count_numled": "6",
    "minipci_ports_port-minipci": "Unknown",
    "model": "RB750UPr2 (hEX PoE lite)",
    "modem_modem": "-",
    "oem_device_homepage_url_url": "https://routerboard.com/RB750UPr2",
    "openvpn_performance": "Unknown",
    "package_architecture_pkg-arch": "mips_24kc",
    "phone_ports_port-phones": "-",
    "power_supply": "8-30 VDC barrel jack, 8-30 VDC passive PoE",
    "ram_mb_mbram": "64",
    "recovery_method(s)_method-recoverys": "unknown",
    "sata_ports_numsataport": "-",
    "serial": "Yes",
    "serial_connection_parameters_serialparam": "115200 / 8N1",
    "serial_connection_voltage_serialvoltage": "Unknown",
    "sfp_plus_ports": "Unknown",
    "sfp_ports": "Unknown",
    "subtarget": "mikrotik",
    "supported_current_rel_releasecurrent": "19.07.10",
    "supported_since_commit_git": "https://git.lede-project.org/?p=source.git;a=commit;h=19f42663d294cfd00770e7c6a9048772e074789d",
    "supported_since_rel_releasesince": "18.06.0",
    "switch": "Qualcomm Atheros QCA9533",
    "target_target": "ar71xx",
    "usb_ports": "1x 2.0",
    "video_ports_port-videos": "-",
    "vlan_yesno": "Yes",
    "where_available": "amazon.com, amazon.de, mikrotik-store.eu",
    "wikidevi_url": "Unknown",
    "wireguard_performance": "Unknown",
    "wlan_2_4ghz": "-",
    "wlan_5_0ghz": "-",
    "wlan_driver_wlan-drivers": "unknown",
    "wlan_hardwares": "-"
}