{
    "availability_availability": "unknown 2018",
    "bluetooth_bluetooth": "Unknown",
    "bootloader": "brnboot",
    "brand": "T-Com / Telekom",
    "cpu": "Lantiq AMAZON-ME",
    "cpu_cores_numcores_": "1",
    "cpu_mhz": "235",
    "detachable_antennas_numdetachantenna": "-",
    "device_page_page": "toh:t-com:spw700v",
    "device_type_devicetype": "WiFi Router",
    "ethernet_100m_ports": "5",
    "ethernet_10gbit_ports": "Unknown",
    "ethernet_1gbit_ports": "-",
    "ethernet_2_5gbit_ports": "Unknown",
    "ethernet_5gbit_ports": "Unknown",
    "fccid": "Unknown",
    "flash_mb_mbflashs": "4",
    "forum_search_search-forums": "Speedport W 700V",
    "git_search_search-gits": "Speedport W 700V",
    "gluon_support_gluonsupport": "unknown",
    "gpios_numgpio": "Unknown",
    "id": "t-comtelekom_speedportw700v",
    "jtag_yesno": "Unknown",
    "minipci_ports_port-minipci": "Unknown",
    "model": "Speedport W 700V",
    "modem_modem": "ADSL2+",
    "openvpn_performance": "Unknown",
    "package_architecture_pkg-arch": "mips_mips32",
    "power_supply": "12 VDC, 1.2 A",
    "ram_mb_mbram": "32",
    "sata_ports_numsataport": "-",
    "serial": "Yes",
    "serial_connection_parameters_serialparam": "Unknown",
    "serial_connection_voltage_serialvoltage": "Unknown",
    "sfp_plus_ports": "Unknown",
    "sfp_ports": "Unknown",
    "subtarget": "ase",
    "supported_current_rel_releasecurrent": "-",
    "supported_since_rel_releasesince": "-",
    "switch": "Infineon ADM6996I",
    "target_target": "lantiq",
    "unsupported_functions_unsupporteds": "WIP",
    "usb_ports": "-",
    "vlan_yesno": "No",
    "wikidevi_id_hwinfo-id": "T-Com_Speedport_W700V",
    "wikidevi_url": "https://wikidevi.wi-cat.ru/T-Com_Speedport_W700V",
    "wireguard_performance": "Unknown",
    "wlan_2_4ghz": "b/g",
    "wlan_5_0ghz": "-",
    "wlan_driver_wlan-drivers": "unknown",
    "wlan_hardwares": "Atheros AR2413"
}