{
    "availability_availability": "Discontinued",
    "bluetooth_bluetooth": "Unknown",
    "bootloader": "RedBoot",
    "brand": "US Robotics",
    "cpu": "Intel IXP422",
    "cpu_cores_numcores_": "1",
    "cpu_mhz": "266",
    "detachable_antennas_numdetachantenna": "-",
    "device_page_page": "toh/us.robotics/usr8200",
    "device_type_devicetype": "Router",
    "ethernet_100m_ports": "5",
    "ethernet_10gbit_ports": "Unknown",
    "ethernet_1gbit_ports": "-",
    "ethernet_2_5gbit_ports": "Unknown",
    "ethernet_5gbit_ports": "Unknown",
    "fccid": "Unknown",
    "flash_mb_mbflashs": "16",
    "forum_search_search-forums": "USR8200",
    "git_search_search-gits": "USR8200",
    "gluon_support_gluonsupport": "unknown",
    "gpios_numgpio": "Unknown",
    "jtag_yesno": "Yes",
    "minipci_ports_port-minipci": "Unknown",
    "model": "USR8200",
    "modem_modem": "-",
    "openvpn_performance": "Unknown",
    "package_architecture_pkg-arch": "armeb_xscale",
    "power_supply": "12 VDC, 3.33 A",
    "ram_mb_mbram": "64",
    "sata_ports_numsataport": "-",
    "serial": "Yes",
    "serial_connection_parameters_serialparam": "Unknown",
    "serial_connection_voltage_serialvoltage": "Unknown",
    "sfp_plus_ports": "Unknown",
    "sfp_ports": "Unknown",
    "subtarget": "generic",
    "switch": "Marvell 88E6060",
    "target_target": "ixp4xx",
    "unsupported_functions_unsupporteds": "WIP",
    "usb_ports": "2x 2.0",
    "vlan_yesno": "Unknown",
    "wikidevi_id_hwinfo-id": "USRobotics_USR8200",
    "wikidevi_url": "https://wikidevi.wi-cat.ru/USRobotics_USR8200",
    "wireguard_performance": "Unknown",
    "wlan_2_4ghz": "-",
    "wlan_5_0ghz": "-",
    "wlan_driver_wlan-drivers": "unknown",
    "wlan_hardwares": "-"
}